task_5_Rakitin_Sergey/__init__.py
task_5_Rakitin_Sergey/collection.py
task_5_rakitin_sergey-0.0.6.dist-info/METADATA
task_5_rakitin_sergey-0.0.6.dist-info/WHEEL
task_5_rakitin_sergey-0.0.6.dist-info/RECORD
