Metadata-Version: 2.3
Name: task_5_Rakitin_Sergey
Version: 0.0.6
Summary: A package for counting unique symbols in a string
Project-URL: Homepage, https://git.foxminded.ua/rakitin-sergey/task_5
Author-email: Rakitin Sergey <dronyx@inbox.ru>
Keywords: count,symbols,unique
Classifier: Operating System :: OS Independent
Classifier: Programming Language :: Python :: 3
Requires-Python: >=3.11
Requires-Dist: python-levenshtein>=0.25.1
